{"guide_accessibility.md":"Bo3EbIZR","guide_button-labels.md":"DPkWLFx-","guide_component-slots.md":"B9PP1BPa","guide_create-a-tour.md":"JspEQcsy","guide_css-theme.md":"BAO00pxk","guide_define-the-content.md":"DBGIop-I","guide_getting-started.md":"BcbZZJwv","guide_hiding-the-arrow.md":"BUPC31wN","guide_highlight-target.md":"DfUjfJEe","guide_jump-options.md":"CMtw4LUH","guide_multiple-tours.md":"s4dL5WFc","guide_roadmap.md":"CAvp42xP","guide_saving-progress.md":"B--oGPh0","guide_scroll-to-element.md":"BdtUGmoD","guide_setting-a-target.md":"D6n2-_Tf","guide_skipping-a-tour.md":"ChSURIvx","guide_start-options.md":"C1WcmV2e","guide_step-highlight-target.md":"p82HWdjt","guide_step-scroll-to-element.md":"BcnfF7BQ","guide_step-using-a-backdrop.md":"-SjF5hnq","guide_the-onafter-event.md":"C_bLvxn3","guide_the-onbefore-event.md":"Blmt1Qci","guide_the-step-type.md":"B3O3Eo97","guide_tour-margin.md":"8LRrqFjB","guide_using-a-backdrop.md":"naJC-kVG","guide_using-placement.md":"CD_xbV2c","guide_what-is-vuejs-tour.md":"CPn5mSxk","index.md":"Cno-bebk"}
